mkalias_foss/__init__.py
mkalias_foss/alias.py
mkalias_foss/log_helper.py
mkalias_foss/mkalias.py
mkalias_foss/version.py
mkalias_foss-1.0.0.dist-info/LICENSE.txt
mkalias_foss-1.0.0.dist-info/METADATA
mkalias_foss-1.0.0.dist-info/WHEEL
mkalias_foss-1.0.0.dist-info/entry_points.txt
mkalias_foss-1.0.0.dist-info/top_level.txt
mkalias_foss-1.0.0.dist-info/RECORD
