Metadata-Version: 2.1
Name: mkalias-foss
Version: 1.0.0
Summary: CLI app to create Finder aliases in OS X
Home-page: https://github.com/iamcb/mkalias
Author: Adam Bennett
Author-email: iamcb@teck90.ca
License: LICENSE.txt
Platform: UNKNOWN
Classifier: Programming Language :: Python :: 3
Classifier: License :: OSI Approved :: GNU General Public License v3 (GPLv3)
Classifier: Operating System :: MacOS :: MacOS X
Requires-Dist: osascript
Requires-Dist: click
